neurodamus/__init__.py
neurodamus/cell_distributor.py
neurodamus/commands.py
neurodamus/connection.py
neurodamus/connection_manager.py
neurodamus/gap_junction.py
neurodamus/gap_junction_user_corrections.py
neurodamus/lfp_manager.py
neurodamus/metype.py
neurodamus/modification_manager.py
neurodamus/morphio_wrapper.py
neurodamus/neuromodulation_manager.py
neurodamus/ngv.py
neurodamus/node.py
neurodamus/replay.py
neurodamus/report.py
neurodamus/report_parameters.py
neurodamus/stimulus_manager.py
neurodamus/target_manager.py
neurodamus/core/__init__.py
neurodamus/core/_engine.py
neurodamus/core/_mpi.py
neurodamus/core/_neurodamus.py
neurodamus/core/_neuron.py
neurodamus/core/_shmutils.py
neurodamus/core/_utils.py
neurodamus/core/configuration.py
neurodamus/core/coreneuron_configuration.py
neurodamus/core/coreneuron_report_config.py
neurodamus/core/coreneuron_simulation_config.py
neurodamus/core/nodeset.py
neurodamus/core/random.py
neurodamus/core/stimuli.py
neurodamus/data/init.py
neurodamus/data/hoc/Cell.hoc
neurodamus/data/hoc/ConnectionUtils.hoc
neurodamus/data/hoc/MorphIO.hoc
neurodamus/data/hoc/RNGSettings.hoc
neurodamus/data/hoc/defvar.hoc
neurodamus/data/hoc/fileUtils.hoc
neurodamus/data/hoc/neurodamus.hoc
neurodamus/data/mod/ALU.mod
neurodamus/data/mod/CoreNEURONArtificialCell.mod
neurodamus/data/mod/SonataReportHelper.mod
neurodamus/data/mod/SonataReports.mod
neurodamus/data/mod/coreneuron_modlist.txt
neurodamus/data/mod/netstim_inhpoisson.mod
neurodamus/io/__init__.py
neurodamus/io/cell_readers.py
neurodamus/io/sonata_config.py
neurodamus/io/synapse_reader.py
neurodamus/utils/__init__.py
neurodamus/utils/cli.py
neurodamus/utils/compat.py
neurodamus/utils/dump_cellstate.py
neurodamus/utils/logging.py
neurodamus/utils/memory.py
neurodamus/utils/multimap.py
neurodamus/utils/progressbar.py
neurodamus/utils/pyutils.py
neurodamus/utils/timeit.py
neurodamus-3.11.0.dist-info/METADATA
neurodamus-3.11.0.dist-info/WHEEL
neurodamus-3.11.0.dist-info/entry_points.txt
neurodamus-3.11.0.dist-info/licenses/LICENSE.txt
neurodamus-3.11.0.dist-info/RECORD
