Metadata-Version: 2.4
Name: neurodamus
Version: 3.11.0
Summary: A BBP Simulation Control application for NEURON
Project-URL: Homepage, https://github.com/BlueBrain/neurodamus
Project-URL: Repository, https://github.com/BlueBrain/neurodamus.git
Project-URL: Tracker, https://github.com/BlueBrain/neurodamus/issues
Author: Blue Brain Project, EPFL
License:                                  Apache License
License-File: LICENSE.txt
Requires-Python: >=3.9
Requires-Dist: docopt-ng
Requires-Dist: h5py
Requires-Dist: libsonata
Requires-Dist: psutil
Provides-Extra: docs
Requires-Dist: sphinx; extra == 'docs'
Requires-Dist: sphinx-bluebrain-theme; extra == 'docs'
Provides-Extra: full
Requires-Dist: morphio; extra == 'full'
Requires-Dist: neuron; extra == 'full'
Requires-Dist: scipy; extra == 'full'
Provides-Extra: plotting
Requires-Dist: matplotlib; extra == 'plotting'
